ssa3021xnoisegui/__init__.py
ssa3021xnoisegui/ssa3021xnoisegui.py
ssa3021xnoisegui_tspspi-0.0.3.dist-info/LICENSE.md
ssa3021xnoisegui_tspspi-0.0.3.dist-info/METADATA
ssa3021xnoisegui_tspspi-0.0.3.dist-info/WHEEL
ssa3021xnoisegui_tspspi-0.0.3.dist-info/entry_points.txt
ssa3021xnoisegui_tspspi-0.0.3.dist-info/top_level.txt
ssa3021xnoisegui_tspspi-0.0.3.dist-info/RECORD
