Metadata-Version: 2.1
Name: ssa3021xnoisegui-tspspi
Version: 0.0.3
Summary: GUI frontend for realtime noise measurements using SSG3021X
Home-page: https://github.com/tspspi/ssa3021xnoisegui
Author: Thomas Spielauer
Author-email: pypipackages01@tspi.at
Classifier: Programming Language :: Python :: 3
Classifier: License :: OSI Approved :: BSD License
Classifier: Operating System :: OS Independent
Requires-Python: >=3.6
License-File: LICENSE.md
Requires-Dist: matplotlib>=3.3.4
Requires-Dist: FreeSimpleGUI>=5.1.0
Requires-Dist: numpy>=1.20.0
Requires-Dist: pylabdevs-tspspi>=0.0.18
Requires-Dist: pyssa3021x-tspspi>=0.0.1
